{
  "parent": "minecraft:recipes/root",
  "criteria": {
    "has_the_recipe": {
      "conditions": {
        "recipe": "betterend:twisted_moss_dye"
      },
      "trigger": "minecraft:recipe_unlocked"
    },
    "has_twisted_moss": {
      "conditions": {
        "items": [
          {
            "items": [
              "betterend:twisted_moss"
            ]
          }
        ]
      },
      "trigger": "minecraft:inventory_changed"
    }
  },
  "requirements": [
    [
      "has_twisted_moss",
      "has_the_recipe"
    ]
  ],
  "rewards": {
    "recipes": [
      "betterend:twisted_moss_dye"
    ]
  },
  "sends_telemetry_event": false
}