{
  "parent": "minecraft:recipes/root",
  "criteria": {
    "has_702_cave_pumpkin": {
      "conditions": {
        "items": [
          {
            "items": [
              "betterend:cave_pumpkin"
            ]
          }
        ]
      },
      "trigger": "minecraft:inventory_changed"
    },
    "has_the_recipe": {
      "conditions": {
        "recipe": "betterend:cave_pumpkin_seeds"
      },
      "trigger": "minecraft:recipe_unlocked"
    }
  },
  "display": {
    "announce_to_chat": false,
    "description": {
      "translate": "advancements.betterend.recipes/decorations/cave_pumpkin_seeds.description"
    },
    "frame": "task",
    "hidden": false,
    "icon": {
      "item": "betterend:cave_pumpkin_seed"
    },
    "show_toast": false,
    "title": {
      "translate": "advancements.betterend.recipes/decorations/cave_pumpkin_seeds.title"
    }
  },
  "requirements": [
    [
      "has_702_cave_pumpkin",
      "has_the_recipe"
    ]
  ],
  "rewards": {
    "recipes": [
      "betterend:cave_pumpkin_seeds"
    ]
  }
}