{
  "parent": "minecraft:recipes/root",
  "criteria": {
    "has_607_needlegrass": {
      "conditions": {
        "items": [
          {
            "items": [
              "betterend:needlegrass"
            ]
          }
        ]
      },
      "trigger": "minecraft:inventory_changed"
    },
    "has_the_recipe": {
      "conditions": {
        "recipe": "betterend:needlegrass_stick"
      },
      "trigger": "minecraft:recipe_unlocked"
    }
  },
  "display": {
    "announce_to_chat": false,
    "description": {
      "translate": "advancements.betterend.recipes/decorations/needlegrass_stick.description"
    },
    "frame": "task",
    "hidden": false,
    "icon": {
      "item": "minecraft:stick"
    },
    "show_toast": false,
    "title": {
      "translate": "advancements.betterend.recipes/decorations/needlegrass_stick.title"
    }
  },
  "requirements": [
    [
      "has_607_needlegrass",
      "has_the_recipe"
    ]
  ],
  "rewards": {
    "recipes": [
      "betterend:needlegrass_stick"
    ]
  }
}